setup.py
edxsdk/__init__.py
edxsdk.egg-info/PKG-INFO
edxsdk.egg-info/SOURCES.txt
edxsdk.egg-info/dependency_links.txt
edxsdk.egg-info/top_level.txt