Metadata-Version: 2.1
Name: edxsdk
Version: 0.1
Summary: edx sdk
Home-page: UNKNOWN
Author: hj
Author-email: 1599712264@qq.com
License: UNKNOWN
Platform: UNKNOWN
